{
    "name": "move: pro beta",
    "description": "",
    "dependencies": {
        "core": "*",
        "microphone": "*",
        "bluetooth": "*",
        "pxt-kitronik-servo-lite": "github:kitronikltd/pxt-kitronik-servo-lite#v1.0.5",
        "servo": "*",
        "move:mini Bluetooth": "pkg:move:mini Bluetooth.json"
    },
    "files": [
        "main.blocks",
        "main.ts",
        "README.md",
        "move:mini Bluetooth.json"
    ],
    "testFiles": [
        "test.ts"
    ],
    "targetVersions": {
        "target": "4.0.18",
        "targetId": "microbit"
    },
    "supportedTargets": [
        "microbit"
    ],
    "preferredEditor": "blocksprj"
}
